MANIFEST.in
Readme.rst
setup.cfg
setup.py
computerwords/__init__.py
computerwords/__main__.py
computerwords/cmd.py
computerwords/config.py
computerwords/library.py
computerwords/plugin.py
computerwords/read_doc_tree.py
computerwords/symbol_tree.py
computerwords.egg-info/PKG-INFO
computerwords.egg-info/SOURCES.txt
computerwords.egg-info/dependency_links.txt
computerwords.egg-info/pbr.json
computerwords.egg-info/requires.txt
computerwords.egg-info/top_level.txt
computerwords/_css/__init__.py
computerwords/_css/default.css
computerwords/_css/normalize.css
computerwords/_html/__init__.py
computerwords/_html/single_page.html
computerwords/cwdom/CWTree.py
computerwords/cwdom/__init__.py
computerwords/cwdom/nodes.py
computerwords/cwdom/traversal.py
computerwords/htmlwriter/__init__.py
computerwords/htmlwriter/util.py
computerwords/htmlwriter/visitors.py
computerwords/markdown_parser/__init__.py
computerwords/markdown_parser/ast.py
computerwords/markdown_parser/cfm_to_cwdom.py
computerwords/markdown_parser/exceptions.py
computerwords/markdown_parser/html_lexer.py
computerwords/markdown_parser/html_parser.py
computerwords/markdown_parser/parse_tree_to_cwdom.py
computerwords/markdown_parser/parse_tree_to_cwdom_util.py
computerwords/markdown_parser/parser_support.py
computerwords/markdown_parser/src_loc.py
computerwords/markdown_parser/tokens.py
computerwords/plugins/__init__.py
computerwords/plugins/callouts.py
computerwords/plugins/graphviz.py
computerwords/plugins/heading_aliases.py
computerwords/plugins/htmlwriter.py
computerwords/plugins/pygments.py
computerwords/plugins/python35.py
computerwords/source_parsers/__init__.py
computerwords/source_parsers/python35.py
computerwords/stdlib/__init__.py
computerwords/stdlib/basics.py
computerwords/stdlib/html.py
computerwords/stdlib/links.py
computerwords/stdlib/table_of_contents.py
tests/CWTestCase.py
tests/__init__.py
tests/test_htmlwriter.py
tests/test_read_doc_tree.py