Metadata-Version: 1.1
Name: computerwords
Version: 1.0a8
Summary: A hopefully pretty good documentation system
Home-page: https://steveasleep.com/computerwords/
Author: Steve Johnson
Author-email: steve@steveasleep.com
License: BSD 3-clause
Download-URL: https://github.com/irskep/computerwords/tarball/1.0a8
Keywords: documentation,docs,markdown
Platform: UNKNOWN
Classifier: Development Status :: 3 - Alpha
Classifier: Intended Audience :: Developers
Classifier: License :: OSI Approved :: BSD License
Classifier: Programming Language :: Python :: 3.5
Classifier: Programming Language :: Python :: 3 :: Only
Classifier: Topic :: Documentation
Classifier: Topic :: Software Development :: Documentation
Classifier: Topic :: Text Processing :: Markup
Requires: CommonMark (>=0.6, <0.7)
Requires: Pygments (>=2.1, <3.0)
